gwyfile/__init__.py
gwyfile/_version.py
gwyfile/objects.py
gwyfile/util.py
gwyfile-0.2.0.dist-info/DESCRIPTION.rst
gwyfile-0.2.0.dist-info/METADATA
gwyfile-0.2.0.dist-info/RECORD
gwyfile-0.2.0.dist-info/WHEEL
gwyfile-0.2.0.dist-info/metadata.json
gwyfile-0.2.0.dist-info/top_level.txt
